primeNumbers_RuXBee/__init__.py
primeNumbers_RuXBee-1.0.dist-info/LICENSE.txt
primeNumbers_RuXBee-1.0.dist-info/METADATA
primeNumbers_RuXBee-1.0.dist-info/WHEEL
primeNumbers_RuXBee-1.0.dist-info/top_level.txt
primeNumbers_RuXBee-1.0.dist-info/RECORD
